.readthedocs.txt
.requirements-dev.txt
MANIFEST.in
Readme.rst
requirements.txt
setup.py
bin/clear.sh
bin/create-statement.sh
bin/diamond-accounting
bin/regdel
bin/sort.sh
bin/sync.sh
diamond_accounting/__init__.py
diamond_accounting/__meta__.py
diamond_accounting/tests.py
diamond_accounting.egg-info/PKG-INFO
diamond_accounting.egg-info/SOURCES.txt
diamond_accounting.egg-info/dependency_links.txt
diamond_accounting.egg-info/not-zip-safe
diamond_accounting.egg-info/requires.txt
diamond_accounting.egg-info/top_level.txt
diamond_accounting/skels/accounting/.gitignore
diamond_accounting/skels/accounting/.mrbob.ini
diamond_accounting/skels/accounting/Makefile
diamond_accounting/skels/accounting/Readme.md
diamond_accounting/skels/accounting/data/.gitignore
diamond_accounting/skels/accounting/etc/ledgerrc
diamond_accounting/skels/accounting/etc/syncrc
diamond_accounting/skels/accounting/ledgers/budget.ledger
diamond_accounting/skels/accounting/ledgers/inbox.ledger
diamond_accounting/skels/accounting/ledgers/main.ledger
diamond_accounting/skels/accounting/ledgers/1999/opening.ledger
diamond_accounting/skels/accounting/products/.gitignore
diamond_accounting/skels/accounting/statements/.gitignore